src/logToTopo/__init__.py
src/logToTopo/argTest.py
src/logToTopo/kwargs.py
src/logToTopo/logToTopo.py
logToTopo-1.1.1.dist-info/LICENSE
logToTopo-1.1.1.dist-info/METADATA
logToTopo-1.1.1.dist-info/WHEEL
logToTopo-1.1.1.dist-info/entry_points.txt
logToTopo-1.1.1.dist-info/top_level.txt
logToTopo-1.1.1.dist-info/RECORD
