Metadata-Version: 2.1
Name: logToTopo
Version: 1.1.1
Summary: A simple topology generation tool
Home-page: https://github.com/laimaretto/logToTopo
Author: Lucas Aimaretto
Author-email: laimaretto@gmail.com
License: BSD 3-clause
Classifier: Programming Language :: Python :: 3
Classifier: License :: OSI Approved :: BSD License
Classifier: Operating System :: OS Independent
Requires-Python: >=3.8
License-File: LICENSE
Requires-Dist: pandas (==1.5.2)
Requires-Dist: pyvis (==0.3.1)
Requires-Dist: logChecker (>=3.5.0)
